MANIFEST.in
README.rst
setup.py
equibel/__init__.py
equibel/asprin.py
equibel/draw.py
equibel/formulagen.py
equibel/graph.py
equibel/graphgen.py
equibel/solver.py
equibel.egg-info/PKG-INFO
equibel.egg-info/SOURCES.txt
equibel.egg-info/dependency_links.txt
equibel.egg-info/requires.txt
equibel.egg-info/top_level.txt
equibel/asp/.DS_Store
equibel/asp/__init__.py
equibel/asp/__init__.pyc
equibel/asp/asprin.lib
equibel/asp/aspypart.lp
equibel/asp/auxilliary/deconstruct.lp
equibel/asp/auxilliary/expanding_card_max.lp
equibel/asp/auxilliary/global_card_max.lp
equibel/asp/auxilliary/symmetric.lp
equibel/asp/auxilliary/transitive.lp
equibel/asp/neighborhoods/ring.lp
equibel/asp/neighborhoods/uspt.lp
equibel/asp/neighborhoods/web.lp
equibel/asp/preferences/augmenting_pref.lp
equibel/asp/preferences/expanding_pref.lp
equibel/asp/preferences/global_pref.lp
equibel/asp/preferences/preference_simple_iteration_const.lp
equibel/asp/problem_encodings/augmenting.lp
equibel/asp/problem_encodings/eq_iterate_const.lp
equibel/asp/problem_encodings/expanding.lp
equibel/asp/problem_encodings/global.lp
equibel/formatters/.DS_Store
equibel/formatters/__init__.py
equibel/formatters/__init__.pyc
equibel/formatters/aspformatter.py
equibel/formatters/aspformatter.pyc
equibel/formatters/bcfformatter.py
equibel/includes/.DS_Store
equibel/includes/__init__.py
equibel/includes/__init__.pyc
equibel/includes/linux_64/__init__.py
equibel/includes/linux_64/asprin.parser
equibel/includes/linux_64/gringo.so
equibel/includes/mac/__init__.py
equibel/includes/mac/__init__.pyc
equibel/includes/mac/asprin.parser
equibel/includes/mac/gringo.so
equibel/parsers/.DS_Store
equibel/parsers/__init__.py
equibel/parsers/__init__.pyc
equibel/parsers/bcfparser.py
equibel/parsers/bcfparser.pyc
equibel/parsers/formulaparser.py
equibel/parsers/formulaparser.pyc
equibel/parsers/parser.out
equibel/parsers/parsetab.py
equibel/parsers/parsetab.pyc