Metadata-Version: 1.1
Name: equibel
Version: 0.9.3a1
Summary: A toolkit for equivalence-based belief change
Home-page: https://github.com/asteroidhouse/equibel
Author: Paul Vicol
Author-email: pvicol@sfu.ca
License: MIT
Keywords: AI,belief change,belief revision,belief merging,multi-agent network
Platform: UNKNOWN
Classifier: Development Status :: 3 - Alpha
Classifier: Intended Audience :: Science/Research
Classifier: Intended Audience :: Developers
Classifier: Topic :: Scientific/Engineering :: Artificial Intelligence
Classifier: License :: OSI Approved :: MIT License
Classifier: Programming Language :: Python :: 2
Classifier: Programming Language :: Python :: 2.7
